<?xml version='1.0' encoding='utf-8'?>
<!-- FreeCAD DocumentObject -->
<Document SchemaVersion="4" FileVersion="2">
<Object name="Chamfer">
  <Properties Count="28" TransientCount="2">
    <_Property name="_Body" type="App::PropertyLinkHidden" status="251658240"/>
    <_Property name="_ElementMapVersion" type="App::PropertyString" status="234881024"/>
    <Property name="AddSubShape" type="Part::PropertyPartShape" status="128">
      <Part ElementMap="0.15.70200.4" brep="1">
<![CDATA[

CASCADE Topology V1, (c) Matra-Datavision
Locations 0
Curve2ds 0
Curves 0
Polygon3D 0
PolygonOnTriangulations 0
Surfaces 0
Triangulations 0

TShapes 0

*]]>
      </Part>
      <ElementMap/>
    </Property>
    <Property name="AddSubType" type="App::PropertyEnumeration" status="12">
      <Integer value="0"/>
    </Property>
    <Property name="Angle" type="App::PropertyAngle">
      <Float value="20"/>
    </Property>
    <Property name="Base" type="App::PropertyLinkSub">
      <LinkSub value="Pad005" count="1">
        <Sub value="Edge43" shadow=";#586;:H4c2,E.Edge43"/>
      </LinkSub>
    </Property>
    <Property name="BaseFeature" type="App::PropertyLink" status="8">
      <Link value="Pad005"/>
    </Property>
    <Property name="ChamferInfo" type="Part::PropertyChamferEdges">
      <EdgeChamferInfo/>
    </Property>
    <Property name="ChamferType" type="App::PropertyEnumeration">
      <Integer value="2"/>
    </Property>
    <Property name="ColoredElements" type="App::PropertyLinkSubHidden" status="218103808">
      <LinkSub value="" count="0">
      </LinkSub>
    </Property>
    <Property name="ExpressionEngine" type="App::PropertyExpressionEngine" status="67108864">
      <ExpressionEngine count="0"></ExpressionEngine>
    </Property>
    <Property name="FixShape" type="App::PropertyEnumeration">
      <Integer value="0"/>
    </Property>
    <Property name="FlipDirection" type="App::PropertyBool">
      <Bool value="false"/>
    </Property>
    <Property name="InvalidShape" type="App::PropertyBool" status="67108864">
      <Bool value="false"/>
    </Property>
    <Property name="Label" type="App::PropertyString" status="134217728">
      <String value="Chamfer"/>
    </Property>
    <Property name="Label2" type="App::PropertyString" status="128">
      <String value=""/>
    </Property>
    <Property name="NewSolid" type="App::PropertyBool">
      <Bool value="false"/>
    </Property>
    <Property name="Placement" type="App::PropertyPlacement" status="8388620">
      <PropertyPlacement Px="0" Py="0" Pz="0" Q0="0" Q1="0" Q2="0" Q3="1" A="0" Ox="0" Oy="0" Oz="1"/>
    </Property>
    <Property name="Refine" type="App::PropertyBool">
      <Bool value="false"/>
    </Property>
    <Property name="Shape" type="Part::PropertyPartShape">
      <Part HasherIndex="0" ElementMap="1.15.70200.4" brep="1">
<![CDATA[

CASCADE Topology V1, (c) Matra-Datavision
Locations 91
1
              1               0               0               0 
              0               1               0               0 
              0               0               1               0 
1
              1               0               0               0 
              0               1               0               0 
              0               0               1               0 
2  2 -1 0
1
              1               0               0               0 
              0               1               0               0 
              0               0               1               0 
1
              1               0               0               0 
              0               1               0               0 
              0               0               1               0 
1
              1 1.07952106938681e-78 4.93038065763132e-32               0 
              0               1 -2.18952885050753e-47               0 
-4.93038065763132e-32 2.18952885050753e-47               1 -3.94430452610506e-31 
1
              1               0               0               0 
              0               1               0               0 
              0               0               1               0 
1
2.22044604925031e-16 2.22044604925031e-16              -1             -13 
             -1 4.93038065763131e-32 -2.22044604925031e-16 -2.88657986402541e-15 
              0               1 2.22044604925031e-16 2.88657986402541e-15 
2  4 1 5 1 6 1 7 1 8 1 2 1 0
2  8 -1 7 -1 6 -1 5 -1 4 -1 0
1
              1               0               0             -10 
              0               1               0 -2.22044604925031e-15 
              0               0               1 2.22044604925031e-15 
2  11 -1 8 -1 7 -1 6 -1 5 -1 4 -1 0
2  7 1 8 1 11 1 2 1 0
1
              1               0               0               0 
              0               1               0               0 
              0               0               1               0 
1
2.22044604925031e-16 2.22044604925031e-16              -1             -11 
             -1 4.93038065763131e-32 -2.22044604925031e-16 -2.44249065417534e-15 
              0               1 2.22044604925031e-16 1.22124532708767e-15 
1
              1               0               0              -2 
              0               1               0 -4.44089209850063e-16 
              0               0               1 4.44089209850063e-16 
2  14 1 15 1 16 1 0
1
              1               0               0               0 
              0               1               0               0 
              0               0               1               0 
1
              1               0               0               0 
              0               1               0               0 
              0               0               1               0 
1
              1 1.07952106938681e-78 4.93038065763132e-32               0 
              0               1 -2.18952885050753e-47 3.94430452610506e-31 
-4.93038065763132e-32 2.18952885050753e-47               1               0 
2  18 1 19 1 20 1 14 1 15 1 16 1 0
2  15 -1 14 -1 20 -1 19 -1 18 -1 0
2  16 -1 15 -1 14 -1 20 -1 19 -1 18 -1 0
2  20 -1 19 -1 18 -1 0
2  4 1 5 1 6 1 7 1 8 1 0
2  2 -1 11 -1 8 -1 7 -1 0
2  14 1 15 1 0
2  18 1 19 1 20 1 14 1 15 1 0
1
              1               0               0               0 
              0               1               0               0 
              0               0               1               0 
1
              1               0               0               0 
              0               1               0               0 
              0               0               1               0 
1
              1 1.34940133673351e-78 3.69778549322349e-32               0 
-1.82314900718588e-63               1 4.93038065763132e-32 1.97215226305253e-31 
-3.69778549322349e-32 -4.93038065763132e-32               1               0 
1
              1               0               0               0 
              0               1               0               0 
              0               0               1               0 
1
2.22044604925031e-16 1.11022302462516e-16              -1              -8 
             -1 3.33066907387547e-16 -2.22044604925031e-16 1.77635683940025e-15 
3.33066907387547e-16               1 1.11022302462516e-16 -2.66453525910038e-15 
1
              1               0               0              -3 
              0               1               0 -6.66133814775094e-16 
              0               0               1 3.33066907387547e-16 
2  29 1 30 1 31 1 32 1 33 1 34 1 0
2  33 -1 32 -1 31 -1 30 -1 29 -1 0
2  34 -1 33 -1 32 -1 31 -1 30 -1 29 -1 0
2  29 1 30 1 31 1 32 1 33 1 0
1
              1               0               0               0 
              0               1               0               0 
              0               0               1               0 
1
              1               0               0               0 
              0               1               0               0 
              0               0               1               0 
1
              1 -4.93038065763132e-32 -5.39760534693403e-78               0 
4.93038065763132e-32               1 -4.93038065763132e-32               0 
2.43086534291451e-63 4.93038065763132e-32               1               0 
1
              1               0               0               0 
              0               1               0               0 
              0               0               1               0 
1
4.44089209850063e-16 -3.33066907387547e-16               1               0 
              1 3.33066907387547e-16 -4.44089209850063e-16               0 
-3.33066907387547e-16               1 3.33066907387547e-16               0 
1
              1               0               0              -8 
              0               1               0 3.5527136788005e-15 
              0               0               1 -2.66453525910038e-15 
2  39 1 40 1 41 1 42 1 43 1 44 1 0
1
2.22044604925031e-16 -3.33066907387547e-16               1               0 
              1 3.33066907387547e-16 -2.22044604925031e-16               0 
-3.33066907387547e-16               1 3.33066907387547e-16               0 
1
              1               0               0               0 
              0               1               0               0 
              0               0               1               0 
2  46 -1 47 -1 41 -1 40 -1 39 -1 0
1
              1               0               0              -8 
              0               1               0 1.77635683940025e-15 
              0               0               1 -2.66453525910038e-15 
2  49 -1 46 -1 47 -1 41 -1 40 -1 39 -1 0
2  43 -1 42 -1 41 -1 40 -1 39 -1 0
2  44 -1 43 -1 42 -1 41 -1 40 -1 39 -1 0
2  32 1 33 1 0
1
              1               0               0               0 
              0               1               0               0 
              0               0               1               0 
1
              1               0               0               0 
              0               1               0               0 
              0               0               1               0 
1
              1 -4.93038065763132e-32 -5.39760534693403e-78               0 
4.93038065763132e-32               1 -4.93038065763132e-32               0 
2.43086534291451e-63 4.93038065763132e-32               1               0 
1
              1               0               0               0 
              0               1               0               0 
              0               0               1               0 
1
4.44089209850063e-16 -3.33066907387547e-16               1               0 
              1 3.33066907387547e-16 -4.44089209850063e-16               0 
-3.33066907387547e-16               1 3.33066907387547e-16               0 
2  54 1 55 1 56 1 57 1 58 1 0
1
2.22044604925031e-16 -3.33066907387547e-16               1               0 
              1 3.33066907387547e-16 -2.22044604925031e-16               0 
-3.33066907387547e-16               1 3.33066907387547e-16               0 
1
              1               0               0               0 
              0               1               0               0 
              0               0               1               0 
2  60 -1 61 -1 56 -1 55 -1 54 -1 0
1
              1               0               0               4 
              0               1               0 -8.88178419700125e-16 
              0               0               1 1.33226762955019e-15 
2  63 -1 60 -1 61 -1 56 -1 55 -1 54 -1 0
1
4.44089209850063e-16 -3.33066907387547e-16               1               0 
              1 3.33066907387547e-16 -4.44089209850063e-16               0 
-3.33066907387547e-16               1 3.33066907387547e-16               0 
2  65 -1 57 -1 56 -1 55 -1 54 -1 0
1
              1               0               0               3 
              0               1               0 -1.33226762955019e-15 
              0               0               1 9.99200722162642e-16 
2  67 -1 65 -1 57 -1 56 -1 55 -1 54 -1 0
2  58 -1 57 -1 56 -1 55 -1 54 -1 0
1
              1               0               0               3 
              0               1               0 -1.33226762955019e-15 
              0               0               1 9.99200722162642e-16 
2  70 -1 58 -1 57 -1 56 -1 55 -1 54 -1 0
1
              1               0               0               0 
              0               1               0               0 
              0               0               1               0 
1
              1               0               0               0 
              0               1               0               0 
              0               0               1               0 
1
              1               0               0               0 
              0               1               0               0 
              0               0               1               0 
1
              1               0               0               0 
              0               1               0               0 
              0               0               1               0 
1
              1 -1.75162308040602e-46 -3.33066907387547e-16 -4.99600361081321e-16 
1.10933564796705e-31               1 3.33066907387547e-16 4.99600361081321e-16 
3.33066907387547e-16 -3.33066907387547e-16               1             1.5 
2  72 1 73 1 74 1 75 1 76 1 0
2  76 -1 75 -1 74 -1 73 -1 72 -1 0
1
              1               0               0 8.87850054751483e-13 
              0               1               0 -8.87850054751484e-13 
              0               0               1 -2665.68078382644 
2  79 -1 76 -1 75 -1 74 -1 73 -1 72 -1 0
1
              1               0               0               0 
              0               1               0               0 
              0               0               1               0 
1
              1               0               0               0 
              0               1               0               0 
              0               0               1               0 
2  72 1 81 1 82 1 75 1 76 1 0
2  76 -1 75 -1 82 -1 81 -1 72 -1 0
1
              1               0               0 8.87850054751483e-13 
              0               1               0 -8.87850054751484e-13 
              0               0               1 -2665.68078382644 
2  85 -1 76 -1 75 -1 82 -1 81 -1 72 -1 0
2  56 1 57 1 58 1 70 1 0
2  54 1 55 1 56 1 57 1 58 1 70 1 0
2  55 -1 54 -1 0
2  57 1 58 1 70 1 2 1 0
2  54 1 55 1 56 1 0
Curve2ds 63
1 0 0 0 -1 
1 6.2831853071795898 0 0 -1 
1 0 0 1 0 
1 0 -8 1 0 
1 0 0 1 0 
1 0 -10 1 0 
8 0 2.1283555449518241
1 6.2831853071795898 0 0 1 
8 0 2.1283555449518241
1 0 0 0 1 
1 0 2.1283555449518241 1 0 
2 -1.3598852146800887e-15 -7.7046958903827773e-17 1 0 -0 1 3.7970595314675957
1 0 0 1 0 
1 0 -2 1 0 
1 0 0 0 -1 
1 6.2831853071795898 0 0 -1 
1 0 0 1 0 
1 0 -3 1 0 
1 0 0 1 0 
1 0 -8 1 0 
1 0 0 1 0 
1 0 -8 1 0 
8 5.9453010585871304 6.6210695557720403
1 9.4247779607693776 0 -1 -0 
1 0 0 1 0 
1 0 -8 1 0 
1 0 0 1 0 
1 0 -8 1 0 
8 3.1415926535897931 3.4794769021822498
1 9.4247779607693829 0 -1 -0 
1 0 0 0 -1 
1 6.2831853071795898 0 0 -1 
8 2.80370840499734 3.1415926535897931
1 3.141592653589794 0 -1 -0 
1 5.9453010585871304 0 0 -1 
1 6.6210695557720403 0 0 -1 
1 0 0 1 0 
1 0 -4 1 0 
1 0 0 1 0 
1 0 -3 1 0 
1 0 0 1 0 
1 0 -3 1 0 
8 5.9453010585871304 6.6210695557720403
1 0 0 1 0 
1 2.80370840499734 0 0 -1 
1 3.4794769021822498 0 0 -1 
1 0 0 1 0 
1 0 -4 1 0 
1 0 0 1 0 
1 0 -3 1 0 
1 0 0 1 0 
1 0 -3 1 0 
8 2.80370840499734 3.4794769021822498
1 0 0 1 0 
1 0 0 1 0 
1 0 -2665.6807838264358 1 0 
1 0 0 1 0 
1 0 -2665.6807838264358 1 0 
1 0 -3 1 0 
2 4.2691480414715084 -3.4512664603419231e-31 -4.4408920985006271e-16 1 -1 -4.4408920985006271e-16 1.5
1 0 -3 1 0 
2 4.2691480414715111 -5.0000000000000009 -4.4408920985006271e-16 1 -1 -4.4408920985006271e-16 1.5
1 5.9453010585871304 0 0 -1 
1 6.6210695557720403 0 0 -1 
1 2.80370840499734 0 0 -1 
1 3.4794769021822498 0 0 -1 
1 0 0 0 -1 
1 6.2831853071795898 0 0 -1 
1 0 0 0 -1 
1 6.2831853071795898 0 0 -1 
Curves 31
1 -12.999999999999998 -4.525000000000003 2.886579864025407e-15 -1 -2.2204460492503131e-16 2.2204460492503131e-16 
2 -21 -4.6629367034256575e-15 4.6629367034256575e-15 -1 -2.2204460492503131e-16 2.2204460492503131e-16 2.2204460492503131e-16 -1 -4.9303806576313238e-32 2.2204460492503131e-16 0 1 4.5250000000000004
2 0 0 0 0 0 1 1 0 -0 -0 1 0 4.5250000000000004
1 -21 -4.5250000000000048 4.6629367034256575e-15 -0.93969262078590854 0.3420201433256686 2.0865367673337432e-16 
2 -23 -5.1070259132757201e-15 5.1070259132757201e-15 -1 -2.2204460492503131e-16 2.2204460492503131e-16 2.2204460492503131e-16 -1 -4.9303806576313238e-32 2.2204460492503131e-16 0 1 3.7970595314675957
2 0 0 0 0 0 1 1 0 -0 -0 1 0 6.5
1 -10.999999999999998 -6.5000000000000027 1.2212453270876732e-15 -1 -2.2204460492503131e-16 2.2204460492503131e-16 
2 0 0 0 0 0 1 1 0 -0 -0 1 0 4.5250000000000004
2 -9.476955898138744e-27 -3.9863693921799258e-43 0 0 0 1 1 0 -0 -0 1 0 4.5250000000000012
2 -9.476955898138744e-27 -3.9863693921799258e-43 0 0 0 1 1 0 -0 -0 1 0 4.5250000000000004
1 -7.9999999999999991 -4.5249999999999986 -1.157407503171726e-15 -1 -2.2204460492503128e-16 1.110223024625157e-16 
1 -4.2691480414715084 1.5 0 1 0 0 
1 2.3954829415513465e-15 4.2691480414715093 -1.5000000000000013 -1 4.4408920985006262e-16 -3.3306690738754726e-16 
1 1.3962822193887051e-15 4.2691480414715111 1.4999999999999987 -1 4.4408920985006262e-16 -3.3306690738754726e-16 
2 -9.476955898138744e-27 -3.9863693921799258e-43 0 0 0 1 1 0 -0 -0 1 0 4.5250000000000012
1 4.2691480414715084 -1.5 0 -1 0 0 
1 -2.3954829415513465e-15 -4.2691480414715093 1.5000000000000013 -1 4.4408920985006262e-16 -3.3306690738754726e-16 
1 -1.3962822193887051e-15 -4.2691480414715111 -1.4999999999999987 -1 4.4408920985006262e-16 -3.3306690738754726e-16 
2 -9.476955898138744e-27 -3.9863693921799258e-43 0 0 0 1 1 0 -0 -0 1 0 4.5250000000000004
1 -4.2691480414715084 1.5 0 1 0 0 
2 0 0 0 0 0 1 1 0 -0 -0 1 0 1.5
2 -5 0 0 0 0 1 1 0 -0 -0 1 0 1.5
1 4.2691480414715084 -1.5 0 -1 0 0 
2 4.9960036108132064e-16 -4.9960036108132074e-16 -1.5 -3.3306690738754711e-16 3.3306690738754716e-16 1 1 1.1093356479670489e-31 3.3306690738754711e-16 0 1 -3.3306690738754716e-16 1.5
2 -5 -4.9960036108132133e-16 -1.5000000000000018 -3.3306690738754711e-16 3.3306690738754716e-16 1 1 1.1093356479670489e-31 3.3306690738754711e-16 0 1 -3.3306690738754716e-16 1.5
1 2.3954829415513465e-15 4.2691480414715093 -1.5000000000000013 1 -4.4408920985006262e-16 3.3306690738754721e-16 
1 1.3962822193887051e-15 4.2691480414715111 1.4999999999999987 1 -4.4408920985006262e-16 3.3306690738754721e-16 
1 -2.3954829415513465e-15 -4.2691480414715093 1.5000000000000013 1 -4.4408920985006262e-16 3.3306690738754721e-16 
1 -1.3962822193887051e-15 -4.2691480414715111 -1.4999999999999987 1 -4.4408920985006262e-16 3.3306690738754721e-16 
1 1.4999999999999996 4.9960036108132094e-16 1.5000000000000004 3.3306690738754711e-16 -3.3306690738754716e-16 -1 
1 -3.5000000000000004 4.9960036108132034e-16 1.4999999999999989 3.3306690738754711e-16 -3.3306690738754716e-16 -1 
Polygon3D 0
PolygonOnTriangulations 0
Surfaces 25
2 -13 -2.886579864025407e-15 2.886579864025407e-15 1 2.2204460492503136e-16 -2.2204460492503131e-16 2.2204460492503136e-16 -1 -1.0947644252537633e-47 2.2204460492503131e-16 4.9303806576313238e-32 1 4.5250000000000004
3 -21 -4.6629367034256575e-15 4.6629367034256575e-15 -1 -2.2204460492503131e-16 2.2204460492503131e-16 2.2204460492503131e-16 -1 -4.9303806576313238e-32 2.2204460492503131e-16 0 1 4.5250000000000004
-0.34906585039886595
1 1.3598852146800889e-15 7.7046958903827625e-17 -3.9443045261050599e-31 0 0 1 1 0 -0 -0 1 0 
1 2.3141294550667156e-15 7.0511271155098256e-18 -1.0372308276832592e-46 0 0 1 1 0 -0 -0 1 0 
2 -11 -2.442490654175344e-15 1.2212453270876732e-15 1 2.2204460492503136e-16 -2.2204460492503131e-16 2.2204460492503136e-16 -1 -1.0947644252537633e-47 2.2204460492503131e-16 4.9303806576313238e-32 1 6.5
2 -8 1.7763568394002491e-15 -2.6645352591003757e-15 1 2.2204460492503131e-16 -1.1102230246251575e-16 2.2204460492503136e-16 -1 3.3306690738754691e-16 1.1102230246251568e-16 3.3306690738754696e-16 1 4.5250000000000004
2 -2.1043069282941627e-42 -9.476955898138744e-27 2.7578234532232514e-42 1 -2.2204460492503121e-16 3.3306690738754696e-16 2.2204460492503131e-16 1 -3.3306690738754701e-16 -3.3306690738754691e-16 3.3306690738754706e-16 1 4.5250000000000012
2 -4.2086138565883259e-42 -9.476955898138744e-27 2.757823453223252e-42 1 -4.4408920985006262e-16 3.3306690738754721e-16 4.4408920985006271e-16 1 -3.3306690738754701e-16 -3.3306690738754706e-16 3.3306690738754716e-16 1 4.5250000000000012
2 -2.1043069282941627e-42 -9.476955898138744e-27 2.7578234532232514e-42 1 -2.2204460492503121e-16 3.3306690738754696e-16 2.2204460492503131e-16 1 -3.3306690738754701e-16 -3.3306690738754691e-16 3.3306690738754706e-16 1 4.5250000000000004
2 -4.2086138565883259e-42 -9.476955898138744e-27 2.757823453223252e-42 1 -4.4408920985006262e-16 3.3306690738754721e-16 4.4408920985006271e-16 1 -3.3306690738754701e-16 -3.3306690738754706e-16 3.3306690738754716e-16 1 4.5250000000000004
1 -3.0219671437335316e-16 1.1747915550196069e-16 -1.1174586265095887e-47 0 0 1 1 0 -0 -0 1 0 
2 -2.1043069282941627e-42 -9.476955898138744e-27 2.7578234532232514e-42 -1 2.2204460492503121e-16 -3.3306690738754696e-16 2.2204460492503131e-16 1 -3.3306690738754701e-16 -3.3306690738754691e-16 3.3306690738754706e-16 1 4.5250000000000012
2 -4.2086138565883259e-42 -9.476955898138744e-27 2.757823453223252e-42 -1 4.4408920985006262e-16 -3.3306690738754721e-16 4.4408920985006271e-16 1 -3.3306690738754701e-16 -3.3306690738754706e-16 3.3306690738754716e-16 1 4.5250000000000012
2 -4.2086138565883259e-42 -9.476955898138744e-27 2.757823453223252e-42 -1 4.4408920985006262e-16 -3.3306690738754721e-16 4.4408920985006271e-16 1 -3.3306690738754701e-16 -3.3306690738754706e-16 3.3306690738754716e-16 1 4.5250000000000012
2 -2.1043069282941627e-42 -9.476955898138744e-27 2.7578234532232514e-42 -1 2.2204460492503121e-16 -3.3306690738754696e-16 2.2204460492503131e-16 1 -3.3306690738754701e-16 -3.3306690738754691e-16 3.3306690738754706e-16 1 4.5250000000000004
2 -4.2086138565883259e-42 -9.476955898138744e-27 2.757823453223252e-42 -1 4.4408920985006262e-16 -3.3306690738754721e-16 4.4408920985006271e-16 1 -3.3306690738754701e-16 -3.3306690738754706e-16 3.3306690738754716e-16 1 4.5250000000000004
2 -4.2086138565883259e-42 -9.476955898138744e-27 2.757823453223252e-42 -1 4.4408920985006262e-16 -3.3306690738754721e-16 4.4408920985006271e-16 1 -3.3306690738754701e-16 -3.3306690738754706e-16 3.3306690738754716e-16 1 4.5250000000000004
1 -2.3954829415513457e-15 -4.2691480414715075 1.5000000000000013 3.3306690738754711e-16 -3.3306690738754716e-16 -1 4.4408920985006271e-16 1 -3.3306690738754701e-16 1 -4.4408920985006262e-16 3.3306690738754726e-16 
2 -4.9960036108132064e-16 4.9960036108132074e-16 1.5 -3.3306690738754711e-16 3.3306690738754716e-16 1 1 1.1093356479670489e-31 3.3306690738754711e-16 0 1 -3.3306690738754716e-16 1.5
2 -5.0000000000000009 4.9960036108132015e-16 1.4999999999999982 -3.3306690738754711e-16 3.3306690738754716e-16 1 1 1.1093356479670489e-31 3.3306690738754711e-16 0 1 -3.3306690738754716e-16 1.5
1 2.3954829415513457e-15 4.2691480414715075 -1.5000000000000013 -3.3306690738754711e-16 3.3306690738754716e-16 1 -4.4408920985006271e-16 -1 3.3306690738754701e-16 1 -4.4408920985006262e-16 3.3306690738754726e-16 
10 -320.68970778252071 329.22869776797506 -341.45954972650355 321.4595497265035
1 2.3954829415513457e-15 4.2691480414715075 -1.5000000000000013 -3.3306690738754711e-16 3.3306690738754716e-16 1 -4.4408920985006271e-16 -1 3.3306690738754701e-16 1 -4.4408920985006262e-16 3.3306690738754726e-16 
1 -2.3954829415513457e-15 -4.2691480414715075 1.5000000000000013 -3.3306690738754706e-16 3.3306690738754716e-16 1 4.4408920985006271e-16 1 -3.3306690738754701e-16 -1 4.4408920985006262e-16 -3.3306690738754721e-16 
1 2.3954829415513457e-15 4.2691480414715075 -1.5000000000000013 3.3306690738754706e-16 -3.3306690738754716e-16 -1 -4.4408920985006271e-16 -1 3.3306690738754701e-16 -1 4.4408920985006262e-16 -3.3306690738754721e-16 
1 7.6635232687437561e-16 3.0654093074975024e-16 1.1335226068056538e-47 0 0 1 1 0 -0 -0 1 0 
Triangulations 0

TShapes 116
Ve
1e-07
-21 -4.525 4.66293670342566e-15
0 0

0101101
*
Ve
1e-07
-13 -4.525 2.88657986402541e-15
0 0

0101101
*
Ed
 1e-07 1 1 0
1  1 0 0 8
3  1 2CN 1 0 0 8
0

0101000
-116 3 +115 0 *
Ed
 1e-07 1 1 0
1  2 0 0 6.28318530717959
2  3 2 0 0 6.28318530717959
2  4 1 2 0 6.28318530717959
0

0101000
+116 0 -116 0 *
Ed
 1e-07 1 1 0
1  3 0 0 6.28318530717959
2  5 1 10 0 6.28318530717959
2  6 1 12 0 6.28318530717959
0

0101000
+115 10 -115 10 *
Wi

0101100
+114 2 +113 0 -112 9 -114 2 *
Fa
0  1e-07 1 0

0101000
+111 3 *
Ve
1e-07
-23 -3.7970595314676 5.10702591327572e-15
0 0

0101101
*
Ed
 1e-07 1 1 0
1  4 0 0 2.12835554495182
3  7 8CN 2 0 0 2.12835554495182
0

0101000
+116 0 -109 0 *
Ed
 1e-07 1 1 0
1  5 0 0 6.28318530717959
2  9 2 0 0 6.28318530717959
2  10 3 13 0 6.28318530717959
0

0101000
+109 0 -109 0 *
Wi

0101100
-108 0 +113 0 -107 0 +108 0 *
Fa
0  0 2 0

0111000
+106 0 *
Ve
1e-07
6.5 3.94430452610506e-31 -3.20474742746036e-31
0 0

0101101
*
Ed
 1e-07 1 1 0
1  6 0 0 6.28318530717959
2  11 5 22 0 6.28318530717959
2  12 5 23 0 6.28318530717959
0

0101100
+104 24 -104 24 *
Wi

0101100
+103 21 *
Wi

0101100
-112 25 *
Fa
0  1e-07 4 17

0101000
+102 0 +101 0 *
Wi

0101100
+107 0 *
Fa
0  1e-07 3 0

0101000
+99 26 *
Ed
 1e-07 1 1 0
1  7 0 0 2
3  13 14CN 5 0 0 2
0

0101000
+104 27 -104 17 *
Wi

0101100
+97 0 -97 0 -103 28 +103 21 *
Fa
0  1e-07 5 0

0101000
+96 0 *
Wi

0101100
+103 28 *
Ve
1.00000001776357e-07
-11 -4.525 -8.24340595784179e-16
0 0

0101101
*
Ed
 1.00000001776357e-07 1 1 0
1  8 0 0 6.28318530717959
2  15 6 36 0 6.28318530717959
2  16 6 37 0 6.28318530717959
0

0101000
+93 37 -93 37 *
Wi

0101100
-92 35 *
Fa
0  1e-07 4 27

0101000
+94 0 +91 0 *
Ve
1.00000003233018e-07
-8 -4.26914804147151 1.5
0 0

0101101
*
Ve
1.00000005475099e-07
-8 4.26914804147151 1.5
0 0

0101101
*
Ed
 1e-07 1 1 0
1  8 0 0.337884248592454 2.80370840499734
2  15 6 36 0.337884248592454 2.80370840499734
2  16 6 37 0.337884248592454 2.80370840499734
0

0101000
+89 36 -88 36 *
Ve
1.00000006661338e-07
-8 4.26914804147151 -1.5
0 0

0101101
*
Ed
 1.00000005475099e-07 1 1 0
1  9 0 5.94530105858713 6.62106955577204
2  17 7 48 5.94530105858713 6.62106955577204
2  18 7 50 5.94530105858713 6.62106955577204
2  19 8 51 5.94530105858713 6.62106955577204
2  20 8 52 5.94530105858713 6.62106955577204
2  21 6 52 5.94530105858713 6.62106955577204
0

0101000
+86 52 -88 52 *
Ve
1.00000004440892e-07
-8 -4.26914804147151 -1.5
0 0

0101101
*
Ed
 1e-07 1 1 0
1  8 0 3.47947690218225 5.94530105858713
2  15 6 36 3.47947690218225 5.94530105858713
2  16 6 37 3.47947690218225 5.94530105858713
0

0101000
+86 36 -84 36 *
Ve
1.00000003662053e-07
-8 -4.525 -1.15740750317173e-15
0 0

0101101
*
Ed
 1.00000003662053e-07 1 1 0
1  10 0 3.14159265358979 3.47947690218225
2  22 9 48 3.14159265358979 3.47947690218225
2  23 9 50 3.14159265358979 3.47947690218225
2  24 10 51 3.14159265358979 3.47947690218225
2  25 10 52 3.14159265358979 3.47947690218225
2  26 6 52 3.14159265358979 3.47947690218225
0

0101000
+82 52 -84 52 *
Ed
 1e-07 1 1 0
1  11 0 0 3
3  27 28CN 6 0 0 3
0

0101000
+82 0 -93 0 *
Ed
 1.00000003233018e-07 1 1 0
1  10 0 2.80370840499734 3.14159265358979
2  22 9 48 2.80370840499734 3.14159265358979
2  23 9 50 2.80370840499734 3.14159265358979
2  24 10 51 2.80370840499734 3.14159265358979
2  25 10 52 2.80370840499734 3.14159265358979
2  29 6 52 2.80370840499734 3.14159265358979
0

0101000
+89 52 -82 52 *
Wi

0101100
-87 38 +85 45 -83 38 +81 45 -80 0 +92 35 +80 0 +79 45 *
Fa
0  1e-07 6 0

0101000
+78 0 *
Ed
 1.00000002664535e-07 1 1 0
1  12 0 0 8.53829608294302
0

0101000
+89 52 -88 52 *
Wi

0101100
-76 45 +87 38 *
Fa
0  1e-07 11 53

0101000
+75 0 *
Ve
1.0000000089509e-07
2.39548294155135e-15 4.26914804147151 -1.5
0 0

0101101
*
Ed
 1.0000000089509e-07 1 1 0
1  13 0 0 8
2  30 8 0 0 8
0

0101000
+73 0 -86 0 *
Ve
1.00000000555112e-07
1.39628221938871e-15 4.26914804147151 1.5
0 0

0101101
*
Ed
 1.00000000555112e-07 1 1 0
1  14 0 0 8
2  31 8 0 0 8
0

0101000
+71 0 -88 0 *
Ed
 1e-07 1 1 0
1  15 0 5.94530105858713 6.62106955577204
2  32 12 62 5.94530105858713 6.62106955577204
2  33 12 64 5.94530105858713 6.62106955577204
2  34 13 66 5.94530105858713 6.62106955577204
2  35 13 68 5.94530105858713 6.62106955577204
2  36 14 69 5.94530105858713 6.62106955577204
2  37 14 71 5.94530105858713 6.62106955577204
2  38 8 69 5.94530105858713 6.62106955577204
0

0101000
+73 69 -71 69 *
Wi

0101100
+72 0 -70 0 -69 59 +85 45 *
Fa
0  1e-07 8 0

0101000
+68 0 *
Ed
 1.00000004440892e-07 1 1 0
1  16 0 0 8.53829608294301
0

0101000
+86 52 -84 52 *
Wi

0101100
+83 38 -66 45 *
Fa
0  1e-07 11 53

0101000
+65 0 *
Ve
1.00000008260059e-07
-2.39548294155135e-15 -4.26914804147151 1.5
0 0

0101101
*
Ed
 1.00000000993014e-07 1 1 0
1  17 0 0 8
2  39 10 0 0 8
0

0101000
+63 0 -89 0 *
Ve
1.00000008260059e-07
-1.39628221938871e-15 -4.26914804147151 -1.5
0 0

0101101
*
Ed
 1.00000000915513e-07 1 1 0
1  18 0 0 8
2  40 10 0 0 8
0

0101000
+61 0 -84 0 *
Ed
 1.00000008038015e-07 1 1 0
1  19 0 2.80370840499734 3.47947690218225
2  41 15 62 2.80370840499734 3.47947690218225
2  42 15 64 2.80370840499734 3.47947690218225
2  43 16 66 2.80370840499734 3.47947690218225
2  44 16 68 2.80370840499734 3.47947690218225
2  45 17 69 2.80370840499734 3.47947690218225
2  46 17 71 2.80370840499734 3.47947690218225
2  47 10 69 2.80370840499734 3.47947690218225
0

0101000
+63 69 -61 69 *
Wi

0101100
+62 0 -60 0 -59 59 +79 45 +81 45 *
Fa
0  1e-07 10 0

0101000
+58 0 *
Ve
1.00000017790319e-07
-1.89560530323005e-14 -1.5 1.5
0 0

0101101
*
Ed
 1e-07 1 1 0
1  20 0 0 2.76914804147151
0

0101000
+63 69 -56 69 *
Ve
1.00000018275454e-07
-1.81062221976533e-14 1.5 1.5
0 0

0101101
*
Ed
 1.00000000222045e-07 1 1 0
1  21 0 1.57079632679491 4.71238898038468
2  48 19 78 1.57079632679491 4.71238898038468
2  49 19 80 1.57079632679491 4.71238898038468
0

0101000
+54 78 -56 78 *
Ed
 1e-07 1 1 0
1  20 0 5.76914804147151 8.53829608294302
0

0101000
+54 69 -71 69 *
Wi

0101100
-55 59 +53 77 -52 59 -70 0 +76 45 +62 0 *
Ve
1.00000000222045e-07
-3.5 4.9960036108132e-16 1.5
0 0

0101101
*
Ed
 1e-07 1 1 0
1  22 0 0 6.28318530717959
2  50 20 84 0 6.28318530717959
2  51 20 86 0 6.28318530717959
0

0101000
+50 84 -50 84 *
Wi

0101100
+49 83 *
Fa
0  1e-07 18 0

0101000
+51 0 +48 0 *
Ve
1.00000018272756e-07
-1.71070214754906e-14 1.5 -1.5
0 0

0101101
*
Ed
 1e-07 1 1 0
1  23 0 0 2.76914804147151
0

0101000
+73 69 -46 69 *
Ve
1.0000001779309e-07
-1.79568523101378e-14 -1.5 -1.5
0 0

0101101
*
Ed
 1.00000000222045e-07 1 1 0
1  24 0 1.57079632679491 4.71238898038468
2  52 19 0 1.57079632679491 4.71238898038468
2  53 22 0 1.57079632679491 4.71238898038468
0

0101000
+46 0 -44 0 *
Ed
 1e-07 1 1 0
1  23 0 5.76914804147151 8.53829608294301
0

0101000
+44 69 -61 69 *
Wi

0101100
-45 59 -43 0 -42 59 -60 0 +66 45 +72 0 *
Ve
1.00000000617655e-07
-3.5 -4.99600361081321e-16 -1.5
0 0

0101101
*
Ed
 1.00000000222045e-07 1 1 0
1  25 0 0 6.28318530717959
2  54 20 0 0 6.28318530717959
2  55 22 0 0 6.28318530717959
0

0101000
+40 0 -40 0 *
Wi

0101100
-39 0 *
Fa
0  1e-07 21 0

0101000
+41 0 +38 0 *
Ve
1.0000000089509e-07
4.26914804147151 -1.5 0
0 0

0101101
*
Ed
 1.0000000089509e-07 1 1 0
1  26 0 0 3
2  56 14 0 0 3
0

0101000
+73 0 -36 87 *
Ve
1.00000000555112e-07
4.26914804147151 1.5 0
0 0

0101101
*
Ed
 1.00000000555112e-07 1 1 0
1  27 0 0 3
2  57 14 0 0 3
0

0101000
+71 0 -34 87 *
Ed
 1e-07 1 1 0
1  15 0 5.94530105858713 6.62106955577204
2  32 12 62 5.94530105858713 6.62106955577204
2  33 12 64 5.94530105858713 6.62106955577204
2  34 13 66 5.94530105858713 6.62106955577204
2  35 13 68 5.94530105858713 6.62106955577204
2  36 14 69 5.94530105858713 6.62106955577204
2  37 14 71 5.94530105858713 6.62106955577204
0

0101000
+36 89 -34 89 *
Wi

0101100
+35 0 -33 0 -69 59 +32 88 *
Fa
0  1e-07 14 0

0101000
+31 0 *
Ve
1.00000000993014e-07
-4.26914804147151 1.5 0
0 0

0101101
*
Ed
 1.00000000993014e-07 1 1 0
1  28 0 0 3
2  58 17 0 0 3
0

0101000
+63 0 -29 87 *
Ve
1.00000000915513e-07
-4.26914804147151 -1.5 0
0 0

0101101
*
Ed
 1.00000000915513e-07 1 1 0
1  29 0 0 3
2  59 17 0 0 3
0

0101000
+61 0 -27 87 *
Ed
 1e-07 1 1 0
1  19 0 2.80370840499734 3.47947690218225
2  41 15 62 2.80370840499734 3.47947690218225
2  42 15 64 2.80370840499734 3.47947690218225
2  43 16 66 2.80370840499734 3.47947690218225
2  44 16 68 2.80370840499734 3.47947690218225
2  45 17 69 2.80370840499734 3.47947690218225
2  46 17 71 2.80370840499734 3.47947690218225
0

0101000
+29 89 -27 89 *
Wi

0101100
+28 0 -26 0 -59 59 +25 88 *
Fa
0  1e-07 17 0

0101000
+24 0 *
Ve
1.00000000222045e-07
1.5 4.99600361081321e-16 1.5
0 0

0101101
*
Ed
 1.00000000222045e-07 1 1 0
1  21 0 4.71238898038468 6.28318530717959
2  48 19 78 4.71238898038468 6.28318530717959
2  49 19 80 4.71238898038468 6.28318530717959
0

0101000
+56 78 -22 78 *
Ed
 1.00000000222045e-07 1 1 0
1  21 0 0 1.57079632679491
2  48 19 78 0 1.57079632679491
2  49 19 80 0 1.57079632679491
0

0101000
+22 78 -54 78 *
Ed
 1e-07 1 1 0
1  20 0 0 8.53829608294302
0

0101000
+29 89 -34 89 *
Wi

0101100
-55 59 -21 77 -20 77 -52 59 -33 0 +19 88 +28 0 *
Fa
0  1e-07 23 0

0101000
+18 0 *
Ve
1.00000000429281e-07
1.5 -4.99600361081321e-16 -1.5
0 0

0101101
*
Ed
 1e-07 1 1 0
1  30 0 0 3
3  60 61CN 19 0 0 3
0

0101000
+22 0 -16 0 *
Ed
 1.00000000222045e-07 1 1 0
1  24 0 4.71238898038468 6.28318530717959
2  52 19 0 4.71238898038468 6.28318530717959
2  53 22 0 4.71238898038468 6.28318530717959
0

0101000
+44 0 -16 0 *
Ed
 1.00000000222045e-07 1 1 0
1  24 0 0 1.57079632679491
2  52 19 0 0 1.57079632679491
2  53 22 0 0 1.57079632679491
0

0101000
+16 0 -46 0 *
Wi

0101100
-15 0 +14 0 +43 0 +13 0 +15 0 -20 77 -53 77 -21 77 *
Fa
0  1e-07 19 0

0101000
+12 0 *
Ed
 1e-07 1 1 0
1  31 0 0 3
3  62 63CN 20 0 0 3
0

0101000
+50 0 -40 0 *
Wi

0101100
-10 0 +39 0 +10 0 -49 83 *
Fa
0  1e-07 20 0

0101000
+9 0 *
Ed
 1e-07 1 1 0
1  23 0 0 8.53829608294301
0

0101000
+36 89 -27 89 *
Wi

0101100
-45 59 +13 0 +14 0 -42 59 -26 0 +7 88 +35 0 *
Fa
0  1e-07 24 0

0101000
+6 0 *
Wi

0101100
+32 91 -19 91 +25 91 -7 91 *
Fa
0  1e-07 25 0

0101000
+4 0 *
Sh

0101100
-110 2 +105 0 +100 2 +98 13 -95 2 -90 2 -77 2 -74 2 +67 2 -64 2 
+57 2 -47 2 -37 2 -30 2 -23 2 +17 2 -11 2 -8 2 +5 2 +3 90 
*
So

0100000
+2 0 *

+1 1 ]]>
      </Part>
      <ElementMap new="1" count="1"><Element key="Dummy" value="Dummy"/></ElementMap>
      <ElementMap2 count="92">
<![CDATA[
23 PostfixCount 12
Edge
Face
Vertex
;:H4c4,V
;:H4c4,E
;:H4c4,F
;:M;CHF;:H4c4:7,E
;:M;CHF;:H4c4:7,F
;:G;CHF;:H4c4:7,F
;:U;CHF;:H4c4:7,E
;:U3;CHF;:H4c4:8,E
;:U;CHF;:H4c4:7,V

MapCount 1

ElementMap 1 23 3

Edge

ChildCount 0

NameCount 46
0
$#681.7 0
$#686.a 0
$#66c.5 0
$#688.a 0
$#688.b 0
$#66b.5 0
$#66a.5 0
$#669.5 0
$#666.5 0
$#662.5 0
$#655.5 0
$#663.5 0
$#664.5 0
$#665.5 0
$#667.5 0
$#65f.5 0
$#653.5 0
$#654.5 0
$#641.5 0
$#65a.5 0
$#660.5 0
$#659.5 0
$#65e.5 0
$#64d.5 0
$#65d.5 0
$#650.5 0
$#661.5 0
$#644.5 0
$#658.5 0
$#64a.5 0
$#65b.5 0
$#63f.5 0
$#640.5 0
$#642.5 0
$#652.5 0
$#64b.5 0
$#656.5 0
$#64e.5 0
$#64f.5 0
$#651.5 0
$#65c.5 0
$#648.5 0
$#646.5 0
$#668.5 0
$#64c.5 0

Face

ChildCount 0

NameCount 21
0
$#682.8 0
$#683.9 0
$#680.6 0
$#684.8 0
$#67f.6 0
$#67e.6 0
$#679.6 0
$#67d.6 0
$#672.6 0
$#67b.6 0
$#67a.6 0
$#678.6 0
$#674.6 0
$#66e.6 0
$#677.6 0
$#671.6 0
$#676.6 0
$#67c.6 0
$#670.6 0
$#673.6 0

Vertex

ChildCount 0

NameCount 28
0
$#68a.c 0
$#63d.4 0
$#68c.c 0
$#63c.4 0
$#63b.4 0
$#63a.4 0
$#637.4 0
$#634.4 0
$#633.4 0
$#635.4 0
$#639.4 0
$#624.4 0
$#626.4 0
$#62e.4 0
$#62c.4 0
$#62f.4 0
$#631.4 0
$#638.4 0
$#628.4 0
$#62b.4 0
$#636.4 0
$#625.4 0
$#627.4 0
$#632.4 0
$#62d.4 0
$#630.4 0
$#62a.4 0

EndMap
]]>
      </ElementMap2>
    </Property>
    <Property name="Size" type="App::PropertyQuantityConstraint">
      <Float value="2"/>
    </Property>
    <Property name="Size2" type="App::PropertyQuantityConstraint" status="4">
      <Float value="1"/>
    </Property>
    <Property name="SupportTransform" type="App::PropertyBool">
      <Bool value="false"/>
    </Property>
    <Property name="Suppress" type="App::PropertyBool">
      <Bool value="false"/>
    </Property>
    <Property name="SuppressedShape" type="Part::PropertyPartShape">
      <Part ElementMap="0.15.70200.4" brep="1">
<![CDATA[

CASCADE Topology V1, (c) Matra-Datavision
Locations 0
Curve2ds 0
Curves 0
Polygon3D 0
PolygonOnTriangulations 0
Surfaces 0
Triangulations 0

TShapes 0

*]]>
      </Part>
      <ElementMap/>
    </Property>
    <Property name="TreeRank" type="App::PropertyInteger" status="2184">
      <Integer value="30"/>
    </Property>
    <Property name="UseAllEdges" type="App::PropertyBool">
      <Bool value="false"/>
    </Property>
    <Property name="ValidateShape" type="App::PropertyBool">
      <Bool value="true"/>
    </Property>
    <Property name="Visibility" type="App::PropertyBool" status="648">
      <Bool value="false"/>
    </Property>
    <Property name="_Siblings" type="App::PropertyLinkList" status="218103808">
      <LinkList count="0">
      </LinkList>
    </Property>
  </Properties>
</Object>
</Document>
